pymysql/__init__.py
pymysql/_auth.py
pymysql/_compat.py
pymysql/_socketio.py
pymysql/charset.py
pymysql/connections.py
pymysql/converters.py
pymysql/cursors.py
pymysql/err.py
pymysql/optionfile.py
pymysql/protocol.py
pymysql/times.py
pymysql/util.py
pymysql/constants/CLIENT.py
pymysql/constants/COMMAND.py
pymysql/constants/CR.py
pymysql/constants/ER.py
pymysql/constants/FIELD_TYPE.py
pymysql/constants/FLAG.py
pymysql/constants/SERVER_STATUS.py
pymysql/constants/__init__.py
anthill_PyMySQL-0.9.999.dist-info/LICENSE
anthill_PyMySQL-0.9.999.dist-info/METADATA
anthill_PyMySQL-0.9.999.dist-info/WHEEL
anthill_PyMySQL-0.9.999.dist-info/top_level.txt
anthill_PyMySQL-0.9.999.dist-info/RECORD
