Metadata-Version: 2.1
Name: anthill-PyMySQL
Version: 0.9.999
Summary: Pure Python MySQL Driver
Home-page: https://github.com/anthill-utils/PyMySQL/
Author: yutaka.matsubara
Author-email: yutaka.matsubara@gmail.com
Maintainer: INADA Naoki
Maintainer-email: songofacandy@gmail.com
License: "MIT"
Project-URL: Documentation, https://pymysql.readthedocs.io/
Keywords: MySQL
Platform: UNKNOWN
Classifier: Development Status :: 5 - Production/Stable
Classifier: Programming Language :: Python :: 2
Classifier: Programming Language :: Python :: 2.7
Classifier: Programming Language :: Python :: 3
Classifier: Programming Language :: Python :: 3.5
Classifier: Programming Language :: Python :: 3.6
Classifier: Programming Language :: Python :: 3.7
Classifier: Programming Language :: Python :: Implementation :: CPython
Classifier: Programming Language :: Python :: Implementation :: PyPy
Classifier: Intended Audience :: Developers
Classifier: License :: OSI Approved :: MIT License
Classifier: Topic :: Database
Provides-Extra: rsa
Requires-Dist: cryptography ; extra == 'rsa'
